MANIFEST.in
README.md
requirement.txt
setup.py
FriedRing/Cfg.py
FriedRing/F2requests.py
FriedRing/FRScript.py
FriedRing/FriedRing.py
FriedRing/__init__.py
FriedRing/fr.py
FriedRing.egg-info/PKG-INFO
FriedRing.egg-info/SOURCES.txt
FriedRing.egg-info/dependency_links.txt
FriedRing.egg-info/entry_points.txt
FriedRing.egg-info/requires.txt
FriedRing.egg-info/top_level.txt
FriedRing.egg-info/zip-safe