Metadata-Version: 1.1
Name: FriedRing
Version: 1.0.9
Summary: this is a FriedRing package for get http request and response.
Home-page: http://blog.csdn.net/crisschan
Author: CrissChan
Author-email: can101208@gmail.com
License: MIT
Keywords: FriedRing python package
Platform: UNKNOWN
Classifier: License :: OSI Approved :: MIT License
Classifier: Development Status :: 5 - Production/Stable
Classifier: Environment :: Console
Classifier: Environment :: Console :: Curses
Classifier: Operating System :: MacOS :: MacOS X
Classifier: Operating System :: POSIX
Classifier: Programming Language :: Python
Classifier: Programming Language :: Python :: 2.7
Classifier: Programming Language :: Python :: Implementation :: CPython
Classifier: Programming Language :: Python :: Implementation :: PyPy
Classifier: Topic :: Internet
Classifier: Topic :: Internet :: WWW/HTTP
Classifier: Topic :: Software Development :: Testing
